hamcom/__init__.py
hamcom-0.0.3.dist-info/LICENSE
hamcom-0.0.3.dist-info/METADATA
hamcom-0.0.3.dist-info/WHEEL
hamcom-0.0.3.dist-info/top_level.txt
hamcom-0.0.3.dist-info/RECORD
