Metadata-Version: 2.1
Name: hamcom
Version: 0.0.3
Summary: Communication-Library for Hamster
Author: Marcel Miljak
Author-email: author@example.com
License: UNKNOWN
Platform: UNKNOWN
Classifier: Programming Language :: Python :: 3
Classifier: License :: OSI Approved :: MIT License
Classifier: Operating System :: OS Independent
Requires-Python: >=3.6
License-File: LICENSE
